finansal_hesaplayici/__init__.py
finansal_hesaplayici/hesaplayici.py
finansal_hesaplayici_zerda-0.1.1.dist-info/METADATA
finansal_hesaplayici_zerda-0.1.1.dist-info/WHEEL
finansal_hesaplayici_zerda-0.1.1.dist-info/top_level.txt
finansal_hesaplayici_zerda-0.1.1.dist-info/RECORD
