Metadata-Version: 2.4
Name: finansal-hesaplayici-zerda
Version: 0.1.1
Summary: Finansal matematik hesaplamaları: peşin değer, gelecek değer ve anüiteler
Author: Zerda Taşir
Requires-Python: >=3.8
